{
	"UCUPCeuGDB81BWRr9sIjz5zw": "ගොම්මන-Gommana",
	"UC7Babk_r2LGv9Yw8SSRXC7g": "Wasthu",
	"UCRaLvUrrj_901Anrljs1F2g": "Sri Lanka Chess Lessons",
	"UC0m6dQOv4kpCyAass0e-UhQ": "Ruwantha denuwan",
	"UC8zE63M96cdRKZSHjCRxRrA": "Wayaexplorers",
	"UC7FbReLMrozkt7r3KVuUtxw": "Centra Home Lands",
	"UCgilhqoyZrXV2EBlaaAtVaw": "Nomadic Indian",
	"UCmi-t34ru5vpG2T5ZnA-5-w": "Smart Fashion With Madu",
	"UCvpoO8WSoTu6vQ6jbK4miBQ": "Kalum Sri",
	"UC5DE-3jtI2qjsaSwusKcIgw": "Beauty of Sri Lanka (BoS)🏕",
	"UC2gpLSHUrXCbWiaBwstZsjg": "Chammi Imalka",
	"UCrlYFNxMXz8H8gzkwjBqzTw": "Manaram tv ( මනරම් )",
	"UCIdPuEgRKgp2_QMKjCVOcGQ": "artWorks!",
	"UC9ZpXicDicbFr4dWXihHn7w": "Shashi Dance Studio ",
	"UCwKYO2L9xzLtWhSv4ncYCIA": "Nilame",
	"UCWmDljD65ZT0mz6Xtizl-og": "Scouting Magazine",
	"UCmY02__u4THbIU1P0fTDsAg": "Craft Hornet",
	"UCMk3TZ_MvwlPbSYp_1FScrw": "Travel With Lahiru",
	"UCN2GByhXeLkilxHV45JwA-A": "Dinesh A Pathum",
	"UCcEz4KkvUrSRAh8LdRnmlCQ": "SL Easy Work",
	"UCZORMicSPLsdNaDSIPdXaGQ": "Maheshi Movie 🇱🇰",
	"UC-_QfYHuzaHAtpHuclu6T5w": "Madu dress Collection",
	"UCS6wii1nENlRXQpu_1mp5CA": "Luxury Sri Lanka",
	"UCALPDRZ1r24z3rdt_AptbTg": "DI's Craft",
	"UCGmMrWmdkyr-7H4ZxlJ89pw": "Madhava Wijesinghe",
	"UC_QNHUH4Ffo7SllYyYqtTUg": "SL Property Collection",
	"UC7YrOQwrPZffUx8tsbZlpGg": "Thuru TV",
	"UCdt6I6JwCeGUwLyCT5bMfZA": "shihara gamage 📽🔔 (  My Channel  )",
	"UCCqftG546XpN1z3Ba4fhIFQ": "Sri Lankan Diver",
	"UCQJc7NshqSToC8QuPa_ccXg": "Thavakaran View",
	"UCpk8Gt--cKfQMun1ZViDLvA": "Manjula property",
	"UCFX0lAkJUQwRP19Oi4BN6bA": "Salahuddin Sumon",
	"UCLqnNzohL8dHs0wdXe0cbyg": "Charu Rajapaksha",
	"UCdvCQ1m7yTUqE9YJv11skrQ": "Fisher King",
	"UCLaAXvkuIl1DBYkGV_A-ApA": "Levi Dean",
	"UC7teTjPtUgURtTBawDA-eFQ": "Amila Nadeeshani",
	"UCaK2FbpgP9b8nqoAQn2VObQ": "Gayan Wickramathilake",
	"UCAHWt3Mq7XHHoP0URYQy2tg": "Miracle Hands",
	"UCTHQT60EJCkIUbuzJsCqMIA": "NS Fashion Sri Lanka",
	"UCX8AKAuHs9TOlN6ADQTf2vw": "Nimas Vlogs",
	"UCo-dnbnOAJX4-TVQ56UQHpA": "coco girl",
	"UCfLyRSkyk2U0vOsiDp7UaRw": "COCO BOY",
	"UCREuGitKem36uuf3Ul95sAQ": "Mudu Rekha",
	"UC5N1qwXhF4fYq_WtuwGz-ww": "Shana Creations",
	"UC2jSHYtmyndA_UA7HI66AOw": "Galle Wedding Films",
	"UCT0FF0XegB5SPE04rgBnaiQ": "Faded Cinematic",
	"UC5dezjl-rF4Sw6BRPM8Q6Zg": "chef sapumal wijesinghe with cooking fever",
	"UC0RWGQFXExJPSdMNf9VAiHg": "C PUTER",
	"UCu4rhIQVcq6_sluqRLMaGAQ": "Ashiya production",
	"UCbUIboW2SEy3smyy_aD_-SQ": "Kangara Agri",
	"UC3vp5WL7Rkto-34Pq_W0cxw": "Gema Music",
	"UCs1HsNzpV2gJRF7IAvDg2ig": "Manuja Art",
	"UCkxOHXK7DRtvU-kg-r4JfZA": "Valvai Sulax",
	"UCJdThrvpDDNpYNyxYhM6UKQ": "Rasaduna රසදුන",
	"UCJUzTbKhMQnTSaEaIma8QKA": "One More Adventure",
	"UCgh0A9J0UqTtYm4qxwrDKmw": "Dayan Kahandawala Academy of Dance",
	"UCI1EIczaKsdOEav8iDugH8w": "Atampahura",
	"UCBcLTjG9p6ELFU8bHvbCmxQ": "House. lk",
	"UCWBE3YZKI2Y4q0JIw-WjEAw": "Kalyani Academic UK",
	"UCaux_7EGmJxl0Rzu5LdoPqw": "Sarasi Dance Academy",
	"UCxARoR_f2IcsmWXe6W8fO0w": "Snooty Fashion",
	"UCsB7IPUQGVpAmn8C9ZXWT7A": "Guy Marchal",
	"UC2a2MMBHVlilu99l1byWPpQ": "DECOR WITH ME LK",
	"UC7lKReUTpOpojf5VM8s59Sg": "SL Anonymous",
	"UCy_WugVxjXC2mrzXGZqvPdQ": "Ovin's Lodge",
	"UCJ0DzLY-VvjWwJcp2soX3wA": "Studio GURRA",
	"UCQwvLoctcjJXa8CkItCf_Kg": "Shiblee Drawing Academy ",
	"UCdJs99QT_6W0syZKV99-GxQ": "SL thusitha bro carpentry",
	"UCoD0z2Sw4n-OCvGq7ZH0Mpg": "Apemai",
	"UCxV_T0pfM8329D4PuT2--Hw": "Uma Fernando",
	"UCgdNIjMy8INRySIV2fMOBAQ": "Startling Homes Design and Consultants",
	"UCTUoH3HvHQ1VAO90wy3VvFw": "Mister T - Real Estate Agency",
	"UCldNvVWIBeCuo-THS9VFLuQ": "Mr Lakiya",
	"UCk7pdRscz2Dm98R9IbU3vHA": "Trust Link",
	"UCniZzdn3_d5q-V-0O54-img": "Deva’s kitchen",
	"UC37UL7Y_a3i04CD3hDoENxQ": "யாழின் யாத்திரிகள் ",
	"UCVYQ3uhBp0FelwxfgDugV_A": "Angling Addicts",
	"UCcHln8llComjF9WGHOe0Ngg": "Yakari යකාරි",
	"UC3u6AmL7DaZNDz67OBg8Pow": "AC land",
	"UCc30sTBdN9LRSxEuHaXV_bQ": "Siyatha TV",
	"UCaZB2gbBjZ9Vff7cSjbGRug": "Business sl",
	"UCNrrHges6MZuXGdUccpLYcw": "SMT TV Machanic Aiya",
	"UCjiCx6QN4ecZONlSDLCOlGQ": "wide a way",
	"UCm92rJL6NSp4WYldNzla9aw": "Travel with Nadun",
	"UClr-cI2Geq6T5h5_UgQ8jWg": "KSTV Lanka",
	"UC_ZD62DVlCA5t2IrQAaeeag": "Travel Girl Shara",
	"UCIHCBtEUwm-WX4OJndFmeLA": "ස්වයං රැකියා පියස _ Best Business Ideas",
	"UCRevgT1hz5vkiJexjjLDXKQ": "Finding Salas",
	"UCp1EFCUOqCMpV1RGvGlQTNw": "Nomad Girl",
	"UCeutmOStla-hxuxehlZHQ1g": "Hiker 360",
	"UCyRZQW_qt1RTzFp8tDMMJXA": "Pro AdPlus ",
	"UCEqQGpC5AV9RrE92CYQH8Ww": "Apstar TV",
	"UCyodDnhyOeM1cByDA69Ihwg": "The Pearl Protectors",
	"UCQ1TR3v32j3JSX0gxeS_7SQ": "TODNO ENGINEERING PVT LTD.",
	"UCIuzHyIsjYxc011HB7QhY_g": "Brokar Home Land",
	"UCx1J_X2V7jpo7ueuo5eT_ag": "Udara Madushan Cinematography",
	"UCSnMh8q_K-IHfqTDJCHPynA": "රියෝ Tech ",
	"UCJahGsxfFJZEpK6F-tu8N-w": "Happy Kids Preschool - Peradeniya",
	"UCZCnkgB_KOJOXyFKLadKwZg": "RV Fancy Bird",
	"UCwuhZm4bHvkQJ6nrQT6JD-Q": "The Traveler Click",
	"UCg7AnukTBguAAZ7wKh0SnxQ": "AL Kalakaraya - AL කලාකාරයා",
	"UC4_Tz25wPK6AuwD8J_2BZQw": "Travel With Ayale",
	"UC0ggQS_GDc818dsLPyde2Kg": "Nalaka Senadeera",
	"UCwNHaKUoFcEBcvvOPniMbag": "Hiking First",
	"UC3elSiek02xB9504tGVv-Xw": "Carrom King",
	"UCcvi9Za-QtM31U-b74etpyA": "Ananmanan TV +",
	"UCi6FGUxJ0qELkA5Cpj8YpUQ": "Adam and Yaz",
	"UCjnm1EigUmIfjPqAC-FCDhw": "ADcafe LK",
	"UCcRriGNb_NjNe3-FCRrnQ9w": "SL Monster Academy",
	"UCPbpvYevpbsYTmTNdLrgWTA": "Udarata.Com",
	"UCAWsHAOwwGGY1XlmsBSPUOQ": "Travel With Lavindu",
	"UCX5ok4mRnvqDclXoFg3PYrA": "BROKER AIYA",
	"UCqtbuE-a7RbRDp_0JYvFrEg": "Kirage Hakkalama",
	"UC8j615lQkUwgvQqruvomQJw": "Ceylon wild trails",
	"UC65RMy_yKe869B91apGcLsQ": "The Tramper",
	"UC5g8US43x6GLcClatUmtz3A": "Easy Ever",
	"UC188PLGQtR2tlbqrsYn_rQw": "Tikiri Hapannu- ටිකිරි හපන්නු",
	"UC1KNe8Yz3_VIsmG-TaSO1-w": "Sihala fm",
	"UCmwbAb6vhz_XTSptO91-kCQ": "බුද්ධ ශ්‍රාවක Dharma Deshana",
	"UCNygT1QYMDoYWRGW38rGPqQ": "Mydea's Craft ",
	"UC8C6-xU8lobZcgJmEJoCDAg": "Rubiks Bro",
	"UCK_MCKUoOzLzW-Fvg94hlWQ": "Wandering Mushto",
	"UCUnq4Vif3A3NTsVeoqcnDXg": "VK Fashion Room",
	"UCDfQzrJWIjj09Qx6n9pPjMg": "Sujatha Gunathilaka",
	"UCV_K_m9EFn20bVuwNUNTrNQ": "ස්වයං රැකියා පියස",
	"UCZIQQz9QtGm0LNLZQeFZoTw": "Walking Diary ~ ඇවිදින දිනපොත",
	"UCNhkjhfLc7vwIOm35GkMYHA": "MADDA",
	"UCJ0lK6vteXvRZ3rGxA3WpRw": " Crazy Handmade DIY",
	"UC95TvSf1vDasyRkYij0bcSQ": "HEDA Traveller",
	"UCkyNzkF4_e6veITiRj0z0oQ": "Infinity",
	"UC7bEZyxJn8_jXDOqa9VkCew": "R & S kitchen",
	"UCnL233zznpCQhdvDRQ3W3cw": "BihanC",
	"UCwlDfJeNfJdg_H7AxWLAYmg": "Time with Shashi",
	"UCpvxae0aQlBKafpC3d2-hmw": "MM Nature Gloss",
	"UCYhsrTdAefbf9IevYuadhkg": "TravelBrothers",
	"UCN-FyGEIHHdME-z-LXrC6ow": "Foot Prints - Dil & Piyu",
	"UCUwcxDM7RfB04JMQIqEl0lw": "SL SUPER HELPER",
	"UCAWzinegUNYm8mCOmyrovEA": "Free Traveller",
	"UCvJbpqqbmJlbxWNe1b4X2gQ": "NP Fashion",
	"UCkFeaqAp5KO7WULzKJsADYA": "brighter sudagala",
	"UCOESdCHWXTwNwmwtEtZlIpw": "Traditional Sri Lankan dance +dabahena dewalaya",
	"UC_JGd1HtLKxlEEosLoC5qGw": "Alex bro",
	"UCMLURyhsP-wN3t7-G0HH7Pw": "Dr.Diaries",
	"UC85FXVmppEQz0dNkmU-wnIA": "Rayaans Craft",
	"UCapWoBUy5JAFwVbk2HI2r-A": "Watapita LK",
	"UCrvhD-nwpx86JHa_tPU7lSQ": "CS Academy ",
	"UC0Um4FbLtKy9PzePN5WesdQ": "Paradise with  Wife ",
	"UC0fnN8-CgXOlHLjGc78e-0g": "UDAYASHANTHA VIDEO TEAM",
	"UC1UDo2FA3p56DIUzTJyl_BA": "AKILA BRO",
	"UCCbm1E52PV05ZLv6dtRB92Q": "Sarrita Jewellery",
	"UCDafiy0r1L8QWjKNE18j6uA": "Ape Charika අපේ චාරිකා",
	"UCd3SYTRbcYapV0O4CJuNRbw": "Lali Bro",
	"UCTpK3XElkVJgP4tRLqGtPZg": "Apparel FM",
	"UCx2z-0SiON3iBjbIBXuaLwA": "Travel With Family",
	"UCZ8OO-3lypeUeAHeGSHwDUQ": "Thozhi suji",
	"UCTLwdGMz7pX4GhdfIyzz6vQ": "𝐃𝐢𝐬𝐧𝐚 𝐓𝐯",
	"UCDqcvWOlZI6k7FNQaVYzfbQ": "Dewmini Sewing Academy",
	"UC8UD8CDFi2kSKxsN2IzJEXQ": "Life With Shiana",
	"UCtI6BPK_Psi1wiVNOuC9S6w": "Santhu Manoj with shaminroo art gallery",
	"UCVvx4GR080Zz_r8WZ7KiBWg": "Reach Real Estate",
	"UCbBKcPEaC7N5rLSl7I_oSLA": "Anjalo Diary",
	"UCkBsPooGuK29wQK8gyd4tFw": "mangala siritha- මංගල සිරිත",
	"UCRppXfq97ZFPsz2WGZ5MiVw": "Yasantha Lakshan Raigama",
	"UCSSDXID14Oq9osHxCDPwf1A": "Soul of Sparrow",
	"UCa4e5sa3a_p2CwwaiU3aNKA": "SL EDITING WITH TECH",
	"UC60CbxhZymE_HDRxCJVxtyw": "DTS Fashion",
	"UCbsv1ddn2gvuHlJm6lAYGQg": "SELAK arts",
	"UCDrADCABwTEfcxp9-NKc6Fw": "ADA Gossip ",
	"UCTUJYXiafW7bIOBIWjXRGKQ": "KvR Tv",
	"UCoyVn5P7r_Uduimsht03asw": "Dance with Rangika",
	"UCr7c-p23fjDvdZsiQaLDSsg": "Fishing Madusanka",
	"UCv6ij8o7Yll3HaWN3qlx6dg": "Kulaja Boii",
	"UCTDkqQ5ZcFbgm4pw-IpkxwQ": "Shasikala Kavindi",
	"UCDR3tnFGtAa-c024JW0OM2A": "Nav_ness",
	"UCcze4dBAneWlQeYPWoVW_vA": "The Fish Kingdom",
	"UCVXzNSjKMPllmAQcXFeWn3Q": "GM Designs",
	"UCEjjOFxqRvqbxd9RmmpNlDQ": "Fisherman Voice",
	"UC3q-D4c4gcTaqHYbE039chQ": "Shivani Bhagya",
	"UC6NaBfF6c3j0fcnE0GqAwDA": "Kavindu Prasanna photography",
	"UCDy34C0ttsrVztxJkJ64diw": "Thamesh Malinda",
	"UCPXalaRSSRHUitjHHvgf1qQ": "Blank Crafts",
	"UCqgSi-ti2hzyWKSDsL3-MMA": "Haritha TV",
	"UC-9l9gXuCCjhijgyVgsep7A": "The Cake Tales by Vandana",
	"UC_QgEc4uqDsRyELXfvtB8Rg": "Dhananja Dance Academy",
	"UCdbtMLY8qRP6ixUfZPDP-IQ": "Hidden Dutchman",
	"UCqUqqCXz_56M-x27dHpgYoA": "Cute Wave",
	"UCrzdS4k99DJr29kEDpXG5fA": "Poorvika Rasasingam",
	"UCaIipOSHMBce-6CokpJTA-w": "ePic Wedding Films - Sri Lanka",
	"UCCzFXdIaS4h1Ii8BbqyNUEg": "SRIYANGI ANU",
	"UC1fDQzWK56vR0V_SwzLwYRQ": "CHENU 'S Aquarium",
	"UC9IRLZ-NivNoZbgW8qJz8-A": "Baby Bella",
	"UCjTczd3HyUelYogB5C1CT6A": "Sujith Real Estate Sri Lanka",
	"UCqgeeuqBQ3sIGYYg5kB-1QA": "Becky'sMilkyWay☆",
	"UCv-v1laHAdoJK6s0lH0CG8A": "Mino Bee",
	"UCt2ObKKYMZlB2QpesMr-7Bw": "Umanda Sasri",
	"UC9xvVhXqZQRKOTR53ohhaoQ": "Camping with Wife",
	"UCGIwp2-xpIniXZvT-dVGpCA": "Upendra Lakshan",
	"UCqaZ13hYuONZDxJwEAGuFjQ": "Gadget City",
	"UCKhUE2q1y3me_zFlit_yJHQ": "Stay Fit with Anju",
	"UC5-A8MI5R4VGXi693d2qq5g": "Uni life with piyu",
	"UCotGWBnixHAJjgNeJcQ179Q": "UD's Journey",
	"UCXLApim8tzHhbRhD6UGU7Kw": "GenKnowHub",
	"UC8ofVmjsFgxYJYN1x5isXAw": "Yasiru Jayakody - Yush",
	"UCxG2bo-dD59q6p7e73qh8vw": "study with hiru",
	"UCPcmmW79sWh8_Kzpeu_w9mA": "Ama H. Vanniarachchy                   Art Studio",
	"UClZjmCu1KeD0Z0slhKUVb6A": "Johan Chrishanth",
	"UC33e0vM5W6gm82W5WuoGB9A": "SL Travel Memo",
	"UCO6230wBO1J4RaMuVJMnW9w": "Travel Geeth",
	"UCwYFLT0vmy4KgdtI3iOHDhA": "Tek Podda",
	"UCADrHmQ1Jpo9LzpvjJSsv7Q": "COLOMBO",
	"UCaaHLcBnuaQabKJBTrGRqtw": "sri pruthiwi",
	"UCEQrXk9S_wxT6fz7Iy7PI5Q": "Аренда жилья на Шри-Ланке - Виктория Планеттэр",
	"UCVlGGBdGaw0fApSQcpVVY4g": "Magegedara",
	"UC4oyuwuK2qs1uruwXtGTJBw": "Sl shanu bro"
}